{
  "appInfo" : {
    "build" : "232.9559.62",
    "buildDate" : "2023-08-23T05:01:12.211Z[UTC]",
    "productCode" : "IC",
    "generated" : "2024-02-24T17:21:08.990673521Z",
    "os" : "Linux 6.2.0-32-generic",
    "runtime" : "JetBrains s.r.o. 17.0.8 17.0.8+7-b1000.8"
  },
  "runtimeInfo" : {
    "maxMemory" : 2147483648,
    "numberOfProcessors" : 8,
    "maxNumberOfIndexingThreads" : 7,
    "maxSizeOfFileForIntelliSense" : 2560000,
    "maxSizeOfFileForContentLoading" : 20971520
  },
  "type" : "Scanning",
  "projectIndexingActivityHistory" : {
    "projectName" : "Student Records",
    "times" : {
      "scanningReason" : "On project open",
      "scanningType" : "FULL_ON_PROJECT_OPEN",
      "scanningId" : 0,
      "creatingIteratorsTime" : 6279675,
      "collectingIndexableFilesTime" : 3026486051,
      "delayedPushPropertiesStageTime" : 660345,
      "indexExtensionsTime" : 226824204,
      "dumbModeStart" : "2024-02-24T17:21:05.926834222Z",
      "dumbWallTimeWithPauses" : 3057042789,
      "dumbWallTimeWithoutPauses" : 3057042789,
      "updatingStart" : "2024-02-24T17:21:05.91585918Z",
      "updatingEnd" : "2024-02-24T17:21:08.983877011Z",
      "totalWallTimeWithPauses" : 3068005477,
      "wallTimeOnPause" : 0,
      "wasInterrupted" : false,
      "totalWallTimeWithoutPauses" : 3068005477
    },
    "fileCount" : {
      "numberOfFileProviders" : 5,
      "numberOfScannedFiles" : 27381,
      "numberOfFilesIndexedByInfrastructureExtensionsDuringScan" : 0,
      "numberOfFilesScheduledForIndexingAfterScan" : 27047
    },
    "scanningStatistics" : [ {
      "providerName" : "JDK 18 /usr/lib/jvm/java-1.18.0-openjdk-amd64",
      "numberOfScannedFiles" : 27162,
      "numberOfSkippedFiles" : 0,
      "numberOfFilesForIndexing" : 26828,
      "numberOfFilesFullyIndexedByInfrastructureExtensions" : 0,
      "filesFullyIndexedByInfrastructureExtensions" : [ ],
      "statusTime" : 1651241520,
      "scanningTime" : 1823761952,
      "timeProcessingUpToDateFiles" : 0,
      "timeUpdatingContentLessIndexes" : 612779469,
      "timeIndexingWithoutContentViaInfrastructureExtension" : 214556305,
      "roots" : [ ]
    }, {
      "providerName" : "Indexable set contributor 'com.intellij.javaee.ExternalResourcesRootsProvider@23b9fd31' (non-project)",
      "numberOfScannedFiles" : 219,
      "numberOfSkippedFiles" : 4,
      "numberOfFilesForIndexing" : 219,
      "numberOfFilesFullyIndexedByInfrastructureExtensions" : 0,
      "filesFullyIndexedByInfrastructureExtensions" : [ ],
      "statusTime" : 507019841,
      "scanningTime" : 539854109,
      "timeProcessingUpToDateFiles" : 0,
      "timeUpdatingContentLessIndexes" : 69993907,
      "timeIndexingWithoutContentViaInfrastructureExtension" : 12267899,
      "roots" : [ ]
    }, {
      "providerName" : "Indexable set contributor 'Scratches & Consoles' (non-project)",
      "numberOfScannedFiles" : 0,
      "numberOfSkippedFiles" : 0,
      "numberOfFilesForIndexing" : 0,
      "numberOfFilesFullyIndexedByInfrastructureExtensions" : 0,
      "filesFullyIndexedByInfrastructureExtensions" : [ ],
      "statusTime" : 0,
      "scanningTime" : 0,
      "timeProcessingUpToDateFiles" : 0,
      "timeUpdatingContentLessIndexes" : 0,
      "timeIndexingWithoutContentViaInfrastructureExtension" : 0,
      "roots" : [ ]
    }, {
      "providerName" : "Indexable set contributor 'Scratches & Consoles' (project)",
      "numberOfScannedFiles" : 0,
      "numberOfSkippedFiles" : 0,
      "numberOfFilesForIndexing" : 0,
      "numberOfFilesFullyIndexedByInfrastructureExtensions" : 0,
      "filesFullyIndexedByInfrastructureExtensions" : [ ],
      "statusTime" : 0,
      "scanningTime" : 0,
      "timeProcessingUpToDateFiles" : 0,
      "timeUpdatingContentLessIndexes" : 0,
      "timeIndexingWithoutContentViaInfrastructureExtension" : 0,
      "roots" : [ ]
    }, {
      "providerName" : "Indexable set contributor 'com.intellij.javaee.ExternalResourcesRootsProvider@23b9fd31' (project)",
      "numberOfScannedFiles" : 0,
      "numberOfSkippedFiles" : 0,
      "numberOfFilesForIndexing" : 0,
      "numberOfFilesFullyIndexedByInfrastructureExtensions" : 0,
      "filesFullyIndexedByInfrastructureExtensions" : [ ],
      "statusTime" : 0,
      "scanningTime" : 0,
      "timeProcessingUpToDateFiles" : 0,
      "timeUpdatingContentLessIndexes" : 0,
      "timeIndexingWithoutContentViaInfrastructureExtension" : 0,
      "roots" : [ ]
    } ]
  }
}